<?xml version="1.0" encoding="UTF-8"?>
<Locators>
 <AppIsFor><![CDATA[//select[@id='pg:Form:appIsFor']]]></AppIsFor>
 	<YoPersInfo>
 		<Title><![CDATA[//input[@id='pg:Form:applicantTitle']]]></Title>
 		<FName><![CDATA[//input[@id='pg:Form:FirstName']]]></FName>
 		<LName><![CDATA[//input[@id='pg:Form:LastName']]]></LName>
 		<CountryOfRes><![CDATA[//select[@id='pg:Form:countryOfResidence']]]></CountryOfRes>
 		<EmailAdd><![CDATA[//input[@id='pg:Form:contactEmail']]]></EmailAdd>
 		<TeleNum><![CDATA[//input[@id='pg:Form:contactPhone']]]></TeleNum>
 	</YoPersInfo>
 	<YourBirthLocation>
 		<Country><![CDATA[//select[@id='pg:Form:country']]]></Country>
 		<ApplicantsBirthState><![CDATA[//input[@id='pg:Form:applicantsBirthState']]]></ApplicantsBirthState>
 		<ApplicantsBirthCity><![CDATA[//input[@id='pg:Form:applicantsBirthCity']]]></ApplicantsBirthCity>
 	</YourBirthLocation>
 	<YourBirthDetails>
 		<Gender><![CDATA[//select[@id='pg:Form:applicantsGender']]]></Gender>
 		<ApplicantsBirthDay><![CDATA[//select[@id='pg:Form:applicantsBirthDay']]]></ApplicantsBirthDay>
 		<ApplicantsBirthMonth><![CDATA[//select[@id='pg:Form:applicantsBirthMonth']]]></ApplicantsBirthMonth>
 		<ApplicantsBirthYear><![CDATA[//input[@id='pg:Form:applicantsBirthYear']]]></ApplicantsBirthYear>
 		<WhereBorn><![CDATA[//select[@id='pg:Form:whereBorn']]]></WhereBorn>
 		<BirthTimeIs><![CDATA[//select[@id='pg:Form:birthTimeIs']]]></BirthTimeIs>
 		<DaylightSavingsTime><![CDATA[//select[@id='pg:Form:daylightSavingsTime']]]></DaylightSavingsTime>
 	</YourBirthDetails>
 	<HealthIssues>
 		<Issue><![CDATA[//input[@id='pg:Form:healthList:0:healthIssue']]]></Issue>
 		<FromDay><![CDATA[//select[@id='pg:Form:healthList:0:fromDay']]]></FromDay>
 		<FromMonth><![CDATA[//select[@id='pg:Form:healthList:0:fromMonth']]]></FromMonth>
 		<FromYear><![CDATA[//input[@id='pg:Form:healthList:0:fromYear']]]></FromYear>
 		<ToDay><![CDATA[//select[@id='pg:Form:healthList:0:toDay']]]></ToDay>
 		<ToMonth><![CDATA[//select[@id='pg:Form:healthList:0:toMonth']]]></ToMonth>
 		<ToYear><![CDATA[//input[@id='pg:Form:healthList:0:toYear']]]></ToYear>
 	</HealthIssues>
 	<Relatives>
 		<Relationship><![CDATA[//input[@id='pg:Form:relLossList:0:errRelationship']]]></Relationship>
 		<Cause><![CDATA[//input[@id='pg:Form:relLossList:0:cause']]]></Cause>
 		<Day><![CDATA[//select[@id='pg:Form:relLossList:0:passingDay']]]></Day>
 		<Month><![CDATA[//select[@id='pg:Form:relLossList:0:passingMonth']]]></Month>
 		<Year><![CDATA[//input[@id='pg:Form:relLossList:0:paasingYear']]]></Year>
 	</Relatives>
 	<RemoveSections>
 		<Relative><![CDATA[//input[@id='pg:Form:relLossList:0:removeRelLoss']]]></Relative>
 		<Marriage><![CDATA[//input[@id='pg:Form:marriageList:0:removeMar']]]></Marriage>
 		<Divorce><![CDATA[//input[@id='pg:Form:divorceList:0:removeDiv']]]></Divorce>
 		<Child><![CDATA[//input[@id='pg:Form:sonDauList:0:removeDiv']]]></Child>
 		<ElderSibling><![CDATA[//input[@id='pg:Form:elderSiblings:0:removeYounger']]]></ElderSibling>
 		<YoungerSibling><![CDATA[//input[@id='pg:Form:youngerSiblings:0:removeElder']]]></YoungerSibling>
 	</RemoveSections>
 	<Marriage>
 		<Event><![CDATA[//input[@id='pg:Form:marriageList:0:eventDes']]]></Event>
 		<Day><![CDATA[//select[@id='pg:Form:marriageList:0:mDay']]]></Day>
 		<Month><![CDATA[//select[@id='pg:Form:marriageList:0:mMonth']]]></Month>
 		<Year><![CDATA[//input[@id='pg:Form:marriageList:0:mYear']]]></Year>
 	</Marriage>
 	<Divorce>
 		<Event><![CDATA[//input[@id='pg:Form:divorceList:0:eventDes']]]></Event>
 		<Day><![CDATA[//select[@id='pg:Form:divorceList:0:dDay']]]></Day>
 		<Month><![CDATA[//select[@id='pg:Form:divorceList:0:dMonth']]]></Month>
 		<Year><![CDATA[//input[@id='pg:Form:divorceList:0:dYear']]]></Year>
 	</Divorce>
 	<Child>
 		<Relationship><![CDATA[//select[@id='pg:Form:sonDauList:0:eventDes']]]></Relationship>
 		<Day><![CDATA[//select[@id='pg:Form:sonDauList:0:dDay']]]></Day>
 		<Month><![CDATA[//select[@id='pg:Form:sonDauList:0:dMonth']]]></Month>
 		<Year><![CDATA[//input[@id='pg:Form:sonDauList:0:dYear']]]></Year>
 	</Child>
 	<ElderSiblings><![CDATA[//select[@id='pg:Form:elderSiblings:0:eventDes']]]></ElderSiblings>
 	<YoungerSiblings><![CDATA[//select[@id='pg:Form:youngerSiblings:0:eventDes']]]></YoungerSiblings>
 	<BodyHeight>
 		<Unit><![CDATA[//select[@id='pg:Form:heightUnit']]]></Unit>
 		<Height><![CDATA[//input[@id='pg:Form:height']]]></Height>
 	</BodyHeight>
 	<BodyWeight>
 		<Unit><![CDATA[//select[@id='pg:Form:weightnUnit']]]></Unit>
 		<Weight><![CDATA[//input[@id='pg:Form:weight']]]></Weight>
 	</BodyWeight>
 	<DecisionMakingPatterns><![CDATA[//select[@id='pg:Form:decisionMakingPattern']]]></DecisionMakingPatterns>
 	<Inheritance><![CDATA[//select[@id='pg:Form:Inheritance']]]></Inheritance>
 	<SubmitForm><![CDATA[//input[@id='pg:Form:UploadBtn']]]></SubmitForm>
 	<DoYouAgree><![CDATA[//select[@id='pg:Form:doYouAgree']]]></DoYouAgree>
 	<PersonalPhoto><![CDATA[//input[@id='files']]]></PersonalPhoto>
 	<SaveImgAndPay><![CDATA[//input[@id='pg:frm:SiteTemplate:submitBtn']]]></SaveImgAndPay>
 	<BillingInfo>
 		<BillingPhone><![CDATA[//input[@id='pg:SiteTemplate:frm:billingPhone']]]></BillingPhone>
 		<BillingStreet><![CDATA[//textarea[@id='pg:SiteTemplate:frm:billingStreet']]]></BillingStreet>
 		<BillingCity><![CDATA[//input[@id='pg:SiteTemplate:frm:billingCity']]]></BillingCity>
 		<Postalcode><![CDATA[//input[@id='pg:SiteTemplate:frm:billingPostalCode']]]></Postalcode>
 		<PayByOther><![CDATA[//input[@id='pg:SiteTemplate:frm:submitBtn3']]]></PayByOther>
 	</BillingInfo>
</Locators>  